AUTHORS
CHANGELOG.txt
DESCRIPTION
LICENSE
MANIFEST.in
setup.py
django_online_docs.egg-info/PKG-INFO
django_online_docs.egg-info/SOURCES.txt
django_online_docs.egg-info/dependency_links.txt
django_online_docs.egg-info/top_level.txt
online_docs/__init__.py
online_docs/app_settings.py
online_docs/models.py
online_docs/urls.py
online_docs/views.py
online_docs/static/online_docs/css/styles.css
online_docs/static/online_docs/js/online_docs.js
online_docs/templates/404.html
online_docs/templates/base.html
online_docs/templates/online_docs/online_docs.html
online_docs/templates/online_docs/online_docs_link.html
online_docs/templates/online_docs/online_docs_view.md
online_docs/templates/online_docs/partials/online_docs.html
online_docs/templatetags/__init__.py
online_docs/templatetags/online_docs_tags.py
online_docs/tests/__init__.py
online_docs/tests/jasmine_tests.py
online_docs/tests/online_docs_tags_tests.py
online_docs/tests/runtests.py
online_docs/tests/test_settings.py
online_docs/tests/urls.py
online_docs/tests/integration_tests/__init__.py
online_docs/tests/integration_tests/views_tests.py
online_docs/tests/jasmine_tests/files.json
online_docs/tests/jasmine_tests/spec/do_stuff.spec.js
online_docs/tests/test_static/js/jquery-1.7.0.min.js
online_docs/tests/test_static/js/jquery-ui-1.8.16.custom.min.js