Metadata-Version: 1.0
Name: django-online-docs
Version: 0.8
Summary: A reusable Django app that shows documentation for the view that is currently
